SAC_pytorch/SAC.py
SAC_pytorch/__init__.py
sac_pytorch-0.0.19.dist-info/METADATA
sac_pytorch-0.0.19.dist-info/WHEEL
sac_pytorch-0.0.19.dist-info/licenses/LICENSE
sac_pytorch-0.0.19.dist-info/RECORD
