Metadata-Version: 2.4
Name: SAC-pytorch
Version: 0.0.19
Summary: Soft Actor Critic - Pytorch
Project-URL: Homepage, https://pypi.org/project/SAC-pytorch/
Project-URL: Repository, https://github.com/lucidrains/SAC-pytorch
Author-email: Phil Wang <lucidrains@gmail.com>
License: MIT License
License-File: LICENSE
Keywords: artificial intelligence,deep learning,reinforcement learning,soft actor critic
Classifier: Development Status :: 4 - Beta
Classifier: Intended Audience :: Developers
Classifier: License :: OSI Approved :: MIT License
Classifier: Programming Language :: Python :: 3.9
Classifier: Topic :: Scientific/Engineering :: Artificial Intelligence
Requires-Python: >=3.9
Requires-Dist: adam-atan2-pytorch>=0.1.18
Requires-Dist: beartype
Requires-Dist: einops>=0.8.1
Requires-Dist: einx[torch]>=0.3.0
Requires-Dist: ema-pytorch>=0.6.2
Requires-Dist: hl-gauss-loss>=0.1.11
Requires-Dist: jaxtyping
Requires-Dist: soft-moe-pytorch>=0.1.6
Requires-Dist: torch>=2.0
Provides-Extra: examples
Provides-Extra: test
Requires-Dist: pytest; extra == 'test'
